hilt/__init__.py
hilt/__version__.py
hilt/cli/__init__.py
hilt/cli/__main__.py
hilt/cli/main.py
hilt/core/__init__.py
hilt/core/actor.py
hilt/core/event.py
hilt/core/exceptions.py
hilt/core/schema.py
hilt/instrumentation/__init__.py
hilt/instrumentation/auto.py
hilt/instrumentation/context.py
hilt/instrumentation/openai_instrumentor.py
hilt/integrations/__init__.py
hilt/integrations/openai.py
hilt/io/__init__.py
hilt/io/reader.py
hilt/io/session.py
hilt/io/writer.py
hilt/utils/__init__.py
hilt/utils/hashing.py
hilt/utils/timestamp.py
hilt/utils/uuid.py
hilt_python-0.2.8.dist-info/METADATA
hilt_python-0.2.8.dist-info/WHEEL
hilt_python-0.2.8.dist-info/entry_points.txt
hilt_python-0.2.8.dist-info/licenses/LICENSE
hilt_python-0.2.8.dist-info/RECORD
