Metadata-Version: 2.4
Name: hilt-python
Version: 0.2.8
Summary: HILT: Human-IA Log Trace - Privacy-first logging format for AI interactions
License: Apache-2.0
License-File: LICENSE
Keywords: ai,logging,llm,privacy,gdpr,openai
Author: HILT Team
Author-email: info@mcsedition.com
Requires-Python: >=3.10,<4.0
Classifier: Development Status :: 3 - Alpha
Classifier: Intended Audience :: Developers
Classifier: License :: OSI Approved :: Apache Software License
Classifier: Programming Language :: Python :: 3
Classifier: Programming Language :: Python :: 3.10
Classifier: Programming Language :: Python :: 3.11
Classifier: Programming Language :: Python :: 3.12
Classifier: Programming Language :: Python :: 3.13
Classifier: Programming Language :: Python :: 3.14
Classifier: Topic :: Software Development :: Libraries :: Python Modules
Provides-Extra: api
Provides-Extra: sheets
Requires-Dist: fastapi (>=0.109.0,<0.110.0) ; extra == "api"
Requires-Dist: google-auth (>=2.23.0,<3.0.0) ; extra == "sheets"
Requires-Dist: gspread (>=6.0.0,<7.0.0) ; extra == "sheets"
Requires-Dist: openai (>=1.0.0,<2.0.0)
Requires-Dist: pydantic (>=2.0,<3.0)
Requires-Dist: python-dotenv (>=1.0.0,<2.0.0) ; extra == "api"
Requires-Dist: uvicorn (>=0.27.0,<0.28.0) ; extra == "api"
Project-URL: Bug Tracker, https://github.com/hilt-format/hilt-python/issues
Project-URL: Documentation, https://hilt-format.org
Project-URL: Homepage, https://hilt-format.org
Project-URL: Repository, https://github.com/hilt-format/hilt-python
